pkgs_test/__init__.py
pkgs_test/data/__init__.py
pkgs_test/data/flatland.txt
pkgs_test/datasets.py
pkgs_test/pkgs_test.py
pkgs_test/plotting.py
pkgs_test-0.2.0.dist-info/LICENSE
pkgs_test-0.2.0.dist-info/METADATA
pkgs_test-0.2.0.dist-info/WHEEL
pkgs_test-0.2.0.dist-info/RECORD
