Metadata-Version: 2.1
Name: pkgs-test
Version: 0.2.0
Summary: test pkgs 
License: MIT
Author: Matthias Heng
Requires-Python: >=3.9,<4.0
Classifier: License :: OSI Approved :: MIT License
Classifier: Programming Language :: Python :: 3
Classifier: Programming Language :: Python :: 3.9
Classifier: Programming Language :: Python :: 3.10
Classifier: Programming Language :: Python :: 3.11
Requires-Dist: matplotlib (==3.6.2)
